odoo/addons/sale_timesheet_task_exclude/README.rst
odoo/addons/sale_timesheet_task_exclude/__init__.py
odoo/addons/sale_timesheet_task_exclude/__manifest__.py
odoo/addons/sale_timesheet_task_exclude/i18n/de.po
odoo/addons/sale_timesheet_task_exclude/i18n/es.po
odoo/addons/sale_timesheet_task_exclude/i18n/sale_timesheet_task_exclude.pot
odoo/addons/sale_timesheet_task_exclude/models/__init__.py
odoo/addons/sale_timesheet_task_exclude/models/project_task.py
odoo/addons/sale_timesheet_task_exclude/readme/CONTRIBUTORS.rst
odoo/addons/sale_timesheet_task_exclude/readme/DESCRIPTION.rst
odoo/addons/sale_timesheet_task_exclude/readme/ROADMAP.rst
odoo/addons/sale_timesheet_task_exclude/readme/USAGE.rst
odoo/addons/sale_timesheet_task_exclude/static/description/icon.png
odoo/addons/sale_timesheet_task_exclude/static/description/index.html
odoo/addons/sale_timesheet_task_exclude/tests/__init__.py
odoo/addons/sale_timesheet_task_exclude/tests/test_sale_timesheet_exclude_task.py
odoo/addons/sale_timesheet_task_exclude/views/project_task.xml
odoo13_addon_sale_timesheet_task_exclude-13.0.1.0.1.dist-info/METADATA
odoo13_addon_sale_timesheet_task_exclude-13.0.1.0.1.dist-info/WHEEL
odoo13_addon_sale_timesheet_task_exclude-13.0.1.0.1.dist-info/top_level.txt
odoo13_addon_sale_timesheet_task_exclude-13.0.1.0.1.dist-info/RECORD
